README.md
setup.py
django_kms/__init__.py
django_kms/cache.py
django_kms/fields.py
django_kms_field.egg-info/PKG-INFO
django_kms_field.egg-info/SOURCES.txt
django_kms_field.egg-info/dependency_links.txt
django_kms_field.egg-info/not-zip-safe
django_kms_field.egg-info/requires.txt
django_kms_field.egg-info/top_level.txt